{
  "rows": [
    {
      "UserID": "1",
      "DatasetName": "Sepsis",
      "Category": "Medical",
      "Size": "2.444MB",
      "Owner": "raz shtrauchler",
      "PublicPrivate": "Public",
      "SharedWithMe": "Yes",
      "PendingApproval": "No"
    },
    {
      "UserID": "2",
      "DatasetName": "Diabetes",
      "Category": "Medical",
      "Size": "11.371MB",
      "Owner": "raz shtrauchler",
      "PublicPrivate": "Public",
      "SharedWithMe": "Yes",
      "PendingApproval": "No"
    },
    {
      "UserID": "3",
      "DatasetName": "Hepatitis",
      "Category": "Medical",
      "Size": "4.007MB",
      "Owner": "raz shtrauchler",
      "PublicPrivate": "Public",
      "SharedWithMe": "Yes",
      "PendingApproval": "No"
    },
    {
      "UserID": "4",
      "DatasetName": "Gesture",
      "Category": "Behavior",
      "Size": "26.288MB",
      "Owner": "yonatan shaya",
      "PublicPrivate": "Private",
      "SharedWithMe": "No",
      "PendingApproval": "Yes"
    },
    {
      "UserID": "5",
      "DatasetName": "FAGender",
      "Category": "Medical",
      "Size": "12.166MB",
      "Owner": "yonatan shaya",
      "PublicPrivate": "Private",
      "SharedWithMe": "Yes",
      "PendingApproval": "No"
    }
  ]
}